ultratime-0.1.2.dist-info/METADATA
ultratime-0.1.2.dist-info/WHEEL
ultratime/__init__.py
ultratime/ultratime.pyd
ultratime-0.1.2.dist-info/RECORD
