Metadata-Version: 2.4
Name: ultratime
Version: 0.1.2
Classifier: Programming Language :: Python
Classifier: Programming Language :: Rust
Classifier: Programming Language :: Python :: Implementation :: CPython
Summary: Super fast datetime alternative
Author-email: Zaky <esrjoo841@email.com>
License-Expression: MIT
Requires-Python: >=3.8
